{
	"home": {
		"big": "you-belong-here",
		"small": ["clue", "interlake-baldies", "healthy-or-harmful", "mental-health-interventions"]
	},
	"issues": {
		"2022-2023": {
			"name": "2022-2023",
			"description": "The Print Issue Year",
			"quarters": {
				"spring": {
					"name": "Spring Issue",
					"articles": []
				},
				"winter": {
					"name": "Winter Issue",
					"articles": []
				}
			}
		},
		"2021-2022": {
			"name": "2021-2022",
			"description": "The \"New Normal\" Year",
			"quarters": {
				"spring": {
					"name": "Spring Issue",
					"articles": []
				},
				"winter": {
					"name": "Winter Issue",
					"articles": []
				}
			}
		},
		"2020-2021": {
			"name": "2020-2021",
			"description": "The Quarantine Year",
			"quarters": {
				"spring": {
					"name": "Spring Issue",
					"articles": []
				},
				"winter": {
					"name": "Winter Issue",
					"articles": []
				}
			}
		},
		"2019-2020": {
			"name": "2019-2020",
			"description": "The Pandemic Year",
			"quarters": {
				"spring": {
					"name": "Spring Issue",
					"articles": []
				},
				"winter": {
					"name": "Winter Issue",
					"articles": []
				}
			}
		}
	}
}
